koala_crawler/__init__.py
koala_crawler/crawlers/__init__.py
koala_crawler/crawlers/crawler_base.py
koala_crawler/crawlers/db/__init__.py
koala_crawler/crawlers/db/db_metadata.py
koala_crawler/crawlers/db/orcale_crawler.py
koala_crawler/crawlers/graph_objects/__init__.py
koala_crawler/crawlers/graph_objects/graph_edge.py
koala_crawler/crawlers/graph_objects/graph_node.py
koala_crawler/crawlers/graph_objects/graph_object_base.py
koala_crawler/exceptions/__init__.py
koala_crawler/exceptions/exceptions.py
koala_crawler-0.0.3.dist-info/METADATA
koala_crawler-0.0.3.dist-info/WHEEL
koala_crawler-0.0.3.dist-info/top_level.txt
koala_crawler-0.0.3.dist-info/RECORD
